prompt_to_query/__init__.py
prompt_to_query/client.py
prompt_to_query/lib/libprompttoquery_darwin_amd64.dylib
prompt_to_query/lib/libprompttoquery_darwin_arm64.dylib
prompt_to_query/lib/libprompttoquery_linux_amd64.so
prompt_to_query/lib/libprompttoquery_linux_amd64_musl.so
prompt_to_query/lib/libprompttoquery_linux_arm64.so
prompt_to_query/lib/libprompttoquery_linux_arm64_musl.so
prompt_to_query/lib/prompttoquery_windows_amd64.dll
prompt_to_query-1.0.9.dist-info/METADATA
prompt_to_query-1.0.9.dist-info/WHEEL
prompt_to_query-1.0.9.dist-info/top_level.txt
prompt_to_query-1.0.9.dist-info/RECORD
