Metadata-Version: 2.4
Name: prompt-to-query
Version: 1.0.9
Summary: High-performance SDK to convert natural language prompts to MongoDB queries using AI (OpenAI GPT or Anthropic Claude)
Home-page: https://github.com/dimarborda/prompt-to-query
Author: Dimar Borda
Author-email: Dimar Borda <dimarborda@gmail.com>
License: MIT
Project-URL: Homepage, https://github.com/dimarb/prompt-to-query
Project-URL: Documentation, https://github.com/dimarb/prompt-to-query#readme
Project-URL: Repository, https://github.com/dimarb/prompt-to-query
Project-URL: Bug Tracker, https://github.com/dimarb/prompt-to-query/issues
Keywords: mongodb,query,natural-language,nlp,ai,llm,openai,gpt,gpt-4,anthropic,claude,database,text-to-query,prompt-engineering,sdk
Classifier: Development Status :: 4 - Beta
Classifier: Intended Audience :: Developers
Classifier: Topic :: Software Development :: Libraries :: Python Modules
Classifier: Topic :: Database
Classifier: Topic :: Scientific/Engineering :: Artificial Intelligence
Classifier: License :: OSI Approved :: MIT License
Classifier: Programming Language :: Python :: 3
Classifier: Programming Language :: Python :: 3.8
Classifier: Programming Language :: Python :: 3.9
Classifier: Programming Language :: Python :: 3.10
Classifier: Programming Language :: Python :: 3.11
Classifier: Programming Language :: Python :: 3.12
Classifier: Operating System :: OS Independent
Classifier: Operating System :: POSIX :: Linux
Classifier: Operating System :: MacOS
Classifier: Operating System :: Microsoft :: Windows
Requires-Python: >=3.8
Dynamic: author
Dynamic: home-page
Dynamic: requires-python
